quisk/CHANGELOG.txt
quisk/__init__.py
quisk/__main__.py
quisk/_quisk.cpython-312-x86_64-linux-gnu.so
quisk/_quisk.pyd
quisk/configure.py
quisk/defaults.html
quisk/docs.html
quisk/dxcluster.py
quisk/filters.py
quisk/help.html
quisk/help_vna.html
quisk/libfftw3-3.dll
quisk/libgcc_s_seh-1.dll
quisk/libusb.txt
quisk/libwdsp.dll
quisk/libwinpthread-1.dll
quisk/license.txt
quisk/midi_handler.py
quisk/portaudio.py
quisk/quisk.py
quisk/quisk_conf_defaults.py
quisk/quisk_conf_kx3.py
quisk/quisk_conf_model.py
quisk/quisk_conf_openradio.py
quisk/quisk_conf_peaberry.py
quisk/quisk_conf_sdr8600.py
quisk/quisk_conf_sdriq.py
quisk/quisk_conf_win.py
quisk/quisk_hardware_fifisdr.py
quisk/quisk_hardware_fixed.py
quisk/quisk_hardware_hamlib.py
quisk/quisk_hardware_hl2_oob.py
quisk/quisk_hardware_model.py
quisk/quisk_hardware_sdr8600.py
quisk/quisk_hardware_sdriq.py
quisk/quisk_utils.py
quisk/quisk_vna.py
quisk/quisk_wdsp.py
quisk/quisk_widgets.py
quisk/softrock_tune_vfo.py
quisk/ac2yd/__init__.py
quisk/ac2yd/control_common.py
quisk/ac2yd/control_hermes.py
quisk/ac2yd/control_hiqsdr.py
quisk/ac2yd/control_softrock.py
quisk/ac2yd/remote_common.py
quisk/ac2yd/remote_hermes.py
quisk/ac2yd/remote_hiqsdr.py
quisk/ac2yd/remote_softrock.py
quisk/afedrinet/SOURCE.txt
quisk/afedrinet/__init__.py
quisk/afedrinet/afedri.py
quisk/afedrinet/afedrinet_io.cpython-312-x86_64-linux-gnu.so
quisk/afedrinet/afedrinet_io.pyd
quisk/afedrinet/quisk_conf.py
quisk/afedrinet/quisk_conf_linux.py
quisk/afedrinet/quisk_conf_mac.py
quisk/afedrinet/quisk_hardware.py
quisk/afedrinet/readme.txt
quisk/afedrinet/sdr_control.py
quisk/afedrinet/setup.py
quisk/afedrinet/test.py
quisk/freedvpkg/README.txt
quisk/freedvpkg/__init__.py
quisk/hermes/README.txt
quisk/hermes/__init__.py
quisk/hermes/hpsdr_widgets.py
quisk/hermes/quisk_conf.py
quisk/hermes/quisk_conf2.py
quisk/hermes/quisk_hardware.py
quisk/hermes/quisk_widgets.py
quisk/hiqsdr/__init__.py
quisk/hiqsdr/quisk_conf.py
quisk/hiqsdr/quisk_hardware.py
quisk-4.2.50.dist-info/METADATA
quisk-4.2.50.dist-info/WHEEL
quisk-4.2.50.dist-info/entry_points.txt
quisk-4.2.50.dist-info/license.txt
quisk-4.2.50.dist-info/top_level.txt
quisk-4.2.50.dist-info/RECORD
