Metadata-Version: 2.1
Name: quisk
Version: 4.2.50
Summary: QUISK is a Software Defined Radio (SDR) transceiver that can control various radio hardware.
Home-page: http://james.ahlstrom.name/quisk/
Author: James C. Ahlstrom
Author-email: jahlstr@gmail.com
Classifier: Development Status :: 6 - Mature
Classifier: Environment :: X11 Applications
Classifier: Environment :: Win32 (MS Windows)
Classifier: Intended Audience :: End Users/Desktop
Classifier: License :: OSI Approved :: GNU General Public License (GPL)
Classifier: Natural Language :: English
Classifier: Operating System :: POSIX :: Linux
Classifier: Operating System :: Microsoft :: Windows
Classifier: Programming Language :: Python :: 3
Classifier: Programming Language :: C
Classifier: Topic :: Communications :: Ham Radio
Provides: quisk
License-File: license.txt
